ustrade/__init__.py
ustrade/client.py
ustrade/codes.py
ustrade/countries.py
ustrade/errors.py
ustrade/data/country_codes.csv
ustrade/data/harmonized-system.csv
ustrade-0.4.0.dist-info/licenses/LICENSE.txt
ustrade-0.4.0.dist-info/METADATA
ustrade-0.4.0.dist-info/WHEEL
ustrade-0.4.0.dist-info/top_level.txt
ustrade-0.4.0.dist-info/RECORD
