Metadata-Version: 2.4
Name: ustrade
Version: 0.4.0
Summary: Python client for the U.S. Census Bureau International Trade API
Author: Fantin Sibony
License-Expression: MIT
Project-URL: Homepage, https://github.com/fantinsib/ustrade
Requires-Python: >=3.10
License-File: LICENSE.txt
Requires-Dist: requests
Requires-Dist: pandas
Dynamic: license-file
